MANIFEST.in
README.md
setup.py
Orange_Vision/__init__.py
Orange_Vision/apps.py
Orange_Vision/camera.py
Orange_Vision/classify.py
Orange_Vision/classify_server.py
Orange_Vision/detect.py
Orange_Vision/detect_server.py
Orange_Vision/svg.py
Orange_Vision/tpu_cam.py
Orange_Vision/utils.py
Orange_Vision.egg-info/PKG-INFO
Orange_Vision.egg-info/SOURCES.txt
Orange_Vision.egg-info/dependency_links.txt
Orange_Vision.egg-info/entry_points.txt
Orange_Vision.egg-info/requires.txt
Orange_Vision.egg-info/top_level.txt
Orange_Vision/CameraManager/TPUCameraManager.py
Orange_Vision/CameraManager/__init__.py
Orange_Vision/CameraManager/ggstreamer.py
Orange_Vision/CameraManager/gst.py
Orange_Vision/CameraManager/gstreamer.py
Orange_Vision/models/field_labels.txt
Orange_Vision/models/mobilenet_v2_edgetpu_red.tflite
Orange_Vision/streaming/__init__.py
Orange_Vision/streaming/server.py
Orange_Vision/streaming/assets/bulma.css
Orange_Vision/streaming/assets/index.html
Orange_Vision/streaming/assets/index_release.html
Orange_Vision/streaming/assets/messages.proto
Orange_Vision/streaming/assets/old.html
Orange_Vision/streaming/assets/protobuf.min.js
Orange_Vision/streaming/assets/settings.html
Orange_Vision/streaming/assets/test.html
Orange_Vision/streaming/assets/ws_client.js
Orange_Vision/streaming/assets/broadway/Decoder.js
Orange_Vision/streaming/assets/broadway/LICENSE
Orange_Vision/streaming/assets/broadway/Player.js
Orange_Vision/streaming/assets/broadway/YUVCanvas.js
Orange_Vision/streaming/assets/css/jquery-ui.css
Orange_Vision/streaming/assets/css/orange-bulma.css
Orange_Vision/streaming/assets/css/orange-core.css
Orange_Vision/streaming/assets/images/favicon.png
Orange_Vision/streaming/assets/images/profile.svg
Orange_Vision/streaming/assets/images/logo/logo-clear.svg
Orange_Vision/streaming/assets/images/logo/logo-grey.svg
Orange_Vision/streaming/assets/images/logo/logo-white.svg
Orange_Vision/streaming/assets/images/logo/orange-grey.svg
Orange_Vision/streaming/assets/images/logo/orange-icon.svg
Orange_Vision/streaming/assets/images/svgs/chest.svg
Orange_Vision/streaming/assets/images/svgs/dive_down.svg
Orange_Vision/streaming/assets/images/svgs/lady.svg
