Metadata-Version: 2.1
Name: Orange-Vision
Version: 0.0.20
Summary: FRC Orange Vision API
Home-page: UNKNOWN
Author: Danny Dasilva
Author-email: dannydasilva.solutions@gmail.com
License: Apache 2
Platform: UNKNOWN
Requires-Python: >=3.5.3
